topsis_Anchit_102203810/__init__.py
topsis_Anchit_102203810/topsis.py
Topsis_Anchit_102203810-1.0.0.dist-info/METADATA
Topsis_Anchit_102203810-1.0.0.dist-info/WHEEL
Topsis_Anchit_102203810-1.0.0.dist-info/entry_points.txt
Topsis_Anchit_102203810-1.0.0.dist-info/top_level.txt
Topsis_Anchit_102203810-1.0.0.dist-info/RECORD
