Metadata-Version: 2.2
Name: Topsis-Anchit-102203810
Version: 1.0.0
Summary: A Python package implementing TOPSIS method for MCDM problems
Home-page: https://github.com/AnMaster15/TOPSES_1
Author: Anchit
Author-email: anchitmehra2018@gmail.com
Classifier: Programming Language :: Python :: 3
Classifier: License :: OSI Approved :: MIT License
Classifier: Operating System :: OS Independent
Requires-Python: >=3.6
Requires-Dist: numpy
Requires-Dist: pandas
Requires-Dist: openpyxl
Dynamic: author
Dynamic: author-email
Dynamic: classifier
Dynamic: description
Dynamic: description-content-type
Dynamic: home-page
Dynamic: requires-dist
Dynamic: requires-python
Dynamic: summary
